zabbix_cli/__about__.py
zabbix_cli/__init__.py
zabbix_cli/__main__.py
zabbix_cli/_types.py
zabbix_cli/_v2_compat.py
zabbix_cli/auth.py
zabbix_cli/bulk.py
zabbix_cli/cache.py
zabbix_cli/dirs.py
zabbix_cli/exceptions.py
zabbix_cli/logs.py
zabbix_cli/main.py
zabbix_cli/models.py
zabbix_cli/py.typed
zabbix_cli/state.py
zabbix_cli/table.py
zabbix_cli/update.py
zabbix_cli/_patches/__init__.py
zabbix_cli/_patches/common.py
zabbix_cli/_patches/typer.py
zabbix_cli/app/__init__.py
zabbix_cli/app/app.py
zabbix_cli/app/plugins.py
zabbix_cli/commands/__init__.py
zabbix_cli/commands/cli.py
zabbix_cli/commands/export.py
zabbix_cli/commands/host.py
zabbix_cli/commands/host_interface.py
zabbix_cli/commands/host_monitoring.py
zabbix_cli/commands/hostgroup.py
zabbix_cli/commands/item.py
zabbix_cli/commands/macro.py
zabbix_cli/commands/maintenance.py
zabbix_cli/commands/media.py
zabbix_cli/commands/problem.py
zabbix_cli/commands/proxy.py
zabbix_cli/commands/template.py
zabbix_cli/commands/templategroup.py
zabbix_cli/commands/user.py
zabbix_cli/commands/usergroup.py
zabbix_cli/commands/common/__init__.py
zabbix_cli/commands/common/args.py
zabbix_cli/commands/results/__init__.py
zabbix_cli/commands/results/cli.py
zabbix_cli/commands/results/export.py
zabbix_cli/commands/results/host.py
zabbix_cli/commands/results/hostgroup.py
zabbix_cli/commands/results/item.py
zabbix_cli/commands/results/macro.py
zabbix_cli/commands/results/maintenance.py
zabbix_cli/commands/results/problem.py
zabbix_cli/commands/results/proxy.py
zabbix_cli/commands/results/template.py
zabbix_cli/commands/results/templategroup.py
zabbix_cli/commands/results/user.py
zabbix_cli/commands/results/usergroup.py
zabbix_cli/config/__init__.py
zabbix_cli/config/__main__.py
zabbix_cli/config/base.py
zabbix_cli/config/commands.py
zabbix_cli/config/constants.py
zabbix_cli/config/model.py
zabbix_cli/config/run.py
zabbix_cli/config/utils.py
zabbix_cli/output/__init__.py
zabbix_cli/output/console.py
zabbix_cli/output/prompts.py
zabbix_cli_uio-3.5.3.dist-info/METADATA
zabbix_cli_uio-3.5.3.dist-info/WHEEL
zabbix_cli_uio-3.5.3.dist-info/entry_points.txt
zabbix_cli_uio-3.5.3.dist-info/licenses/AUTHORS
zabbix_cli_uio-3.5.3.dist-info/licenses/LICENSE
zabbix_cli_uio-3.5.3.dist-info/RECORD
