Metadata-Version: 2.4
Name: zabbix-cli-uio
Version: 3.5.3
Summary: ZABBIX-CLI - Zabbix terminal client
Project-URL: Documentation, https://github.com/unioslo/zabbix-cli#readme
Project-URL: Issues, https://github.com/unioslo/zabbix-cli/issues
Project-URL: Source, https://github.com/unioslo/zabbix-cli
Author: Others (see AUTHORS)
Author-email: Rafael Martinez Guerrero <rafael@postgresql.org.es>, Paal Braathen <paal.braathen@usit.uio.no>, Marius Bakke <marius.bakke@usit.uio.no>
Maintainer-email: Peder Hovdan Andresen <pederhan@uio.no>
License-Expression: GPL-3.0-or-later
License-File: AUTHORS
License-File: LICENSE
Classifier: Development Status :: 4 - Beta
Classifier: Development Status :: 5 - Production/Stable
Classifier: Environment :: Console
Classifier: Intended Audience :: System Administrators
Classifier: License :: OSI Approved :: GNU General Public License v3 or later (GPLv3+)
Classifier: Programming Language :: Python
Classifier: Programming Language :: Python :: 3.9
Classifier: Programming Language :: Python :: 3.10
Classifier: Programming Language :: Python :: 3.11
Classifier: Programming Language :: Python :: 3.12
Classifier: Programming Language :: Python :: 3.13
Classifier: Programming Language :: Python :: Implementation :: CPython
Classifier: Topic :: System :: Monitoring
Requires-Python: >=3.9
Requires-Dist: httpx[socks]>=0.28.1
Requires-Dist: importlib-metadata>=8.5.0; python_version < '3.10'
Requires-Dist: packaging>=22.0
Requires-Dist: platformdirs>=2.5.4
Requires-Dist: prompt-toolkit>=3.0.47
Requires-Dist: pydantic>=2.7.0
Requires-Dist: rich>=13.3.1
Requires-Dist: strenum>=0.4.15
Requires-Dist: tomli-w>=1.0.0
Requires-Dist: tomli>=2.0.1; python_version < '3.11'
Requires-Dist: typer>=0.13.1
Requires-Dist: typing-extensions>=4.8.0
